[
  { "en": "to abandon", "he": "לנטוש" },
  { "en": "absence", "he": "העדר, היעדרות, חוסר" },
  { "en": "absent", "he": "נעדר" },
  { "en": "abrupt", "he": "פתאומי" },
  { "en": "to absorb", "he": "לספוג" },
  { "en": "accessory", "he": "אביזר, שותף לדבר עבירה" },
  { "en": "acclaimed", "he": "מהולל, שזכה לשבחי הביקורת" },
  { "en": "acquaintance", "he": "מכר" },
  { "en": "acquisition", "he": "רכישה, קניין" },
  { "en": "to acquire", "he": "לרכוש, לקנות" },
  { "en": "affirmative", "he": "חיובי" },
  { "en": "affirmative action", "he": "אפליה מתקנת" },
  { "en": "agriculture", "he": "חקלאות" },
  { "en": "to alter", "he": "לשנות" },
  { "en": "to announce", "he": "להכריז" },
  { "en": "to anticipate", "he": "לצפות, לצפות מראש" },
  { "en": "appeal", "he": "משיכה/קסם, פנייה/עתירה, תחנון/ערעור" },
  { "en": "appliances", "he": "מכשירי חשמל" },
  { "en": "to apprehend", "he": "ללכוד, לתפוס" },
  { "en": "apprehension", "he": "לכידה/תפיסה, חשש/דאגה" },
  { "en": "arbitrary", "he": "שרירותי" },
  { "en": "arbitrator", "he": "בורר" },
  { "en": "arrogant", "he": "שחצן, יהיר" },
  { "en": "to ascend", "he": "לעלות, להתרומם, להתנשא" },
  { "en": "attempt", "he": "ניסיון" },
  { "en": "to attempt", "he": "לנסות" },
  { "en": "to attend", "he": "לנכוח" },
  { "en": "attribute", "he": "תכונה" },
  { "en": "to attribute", "he": "לייחס, לזקוף" },
  { "en": "award", "he": "פרס" },
  { "en": "to ban", "he": "לאסור, להחרים, לנדות" },
  { "en": "barely", "he": "בקושי" },
  { "en": "bark", "he": "קליפת גזע העץ, נביחה" },
  { "en": "benign", "he": "טוב, שפיר" },
  { "en": "blade", "he": "להב" },
  { "en": "breed", "he": "זן, גזע" },
  { "en": "to breed", "he": "לגדל, להרביע" },
  { "en": "broad", "he": "רחב" },
  { "en": "calf", "he": "עגל, שוק (חלק הרגל האחורי, בין הברך לקרסול)" },
  { "en": "to carve", "he": "לחרוט, לגלף, לחקוק, לפרוס, לחתוך, לבתר" },
  { "en": "casualty", "he": "נפגע, חלל (מת)" },
  { "en": "cellar", "he": "מרתף" },
  { "en": "clergy", "he": "מעמד הכמורה" },
  { "en": "clerical", "he": "פקידותי, ששייך לכמורה" },
  { "en": "chariot", "he": "מרכבה" },
  { "en": "coal", "he": "פחם" },
  { "en": "collaboration", "he": "שיתוף פעולה" },
  { "en": "to collide", "he": "להתנגש" },
  { "en": "to commence", "he": "להתחיל" },
  { "en": "commerce", "he": "מסחר" },
  { "en": "commercial", "he": "מסחרי, פרסומת בטלוויזיה" },
  { "en": "to compensate", "he": "לפצות" },
  { "en": "to comprehend", "he": "להבין" },
  { "en": "comprehensive", "he": "מקיף" },
  { "en": "compulsory", "he": "חובה" },
  { "en": "to conceal", "he": "להסוות, להסתיר" },
  { "en": "to condemn", "he": "לגנות, להרשיע" },
  { "en": "to condescend", "he": "להתנשא מעל מישהו, להתייהר" },
  { "en": "condescending", "he": "מתנשא" },
  { "en": "to condone", "he": "למחול, לסלוח, לחנון, להתיר את קיומו של" },
  { "en": "concise", "he": "תמציתי" },
  { "en": "to concur", "he": "להתאים, לתאם, לעלות בקנה אחד, להסכים" },
  { "en": "constant", "he": "קבוע, רצוף, יציב" },
  { "en": "constantly", "he": "באופן קבוע, באופן מתמיד" },
  { "en": "contagious", "he": "מידבק" },
  { "en": "contemporary", "he": "בן זמננו, עכשווי, מודרני" },
  { "en": "contest", "he": "תחרות" },
  { "en": "corpse", "he": "גופה, גוויה" },
  { "en": "to crawl", "he": "לזחול" },
  { "en": "damp", "he": "לח" },
  { "en": "debt", "he": "חוב" },
  { "en": "to declare", "he": "להצהיר" },
  { "en": "to deceive", "he": "לרמות" },
  { "en": "decline", "he": "ירידה, צמצום, מדרון" },
  { "en": "to decline", "he": "לסרב, לדחות, לקטון, להצטמצם" },
  { "en": "to deduce", "he": "להסיק" },
  { "en": "to deduct", "he": "לנכות, להפחית" },
  { "en": "deficiency", "he": "פגם, לקות, ליקוי, חסך, מחסור" },
  { "en": "deficient", "he": "לקוי, לוקה בחסר, נטול, משולל" },
  { "en": "dense", "he": "צפוף, דחוס" },
  { "en": "density", "he": "צפיפות" },
  { "en": "to deprive", "he": "לקפח, למנוע, לשלול (זכות)" },
  { "en": "deprivation", "he": "קיפוח, מניעה, חסר, חסך, מחסור" },
  { "en": "derision", "he": "לעג, לגלוג, בוז" },
  { "en": "to descend", "he": "לרדת" },
  { "en": "descendant", "he": "צאצא" },
  { "en": "to despise", "he": "לבוז, לתעב" },
  { "en": "to deteriorate", "he": "להתדרדר" },
  { "en": "detrimental", "he": "מזיק, שלילי" },
  { "en": "devastating", "he": "הרסני" },
  { "en": "to devise", "he": "להגות, לתכנן" },
  { "en": "dignified", "he": "מכובד" },
  { "en": "diligence", "he": "חריצות, שקדנות, התמדה" },
  { "en": "disguise", "he": "תחפושת, מסווה" },
  { "en": "dispute", "he": "ויכוח, פולמוס, ריב" },
  { "en": "to dispute", "he": "להתווכח, לקרוא תיגר על" },
  { "en": "distinct", "he": "ברור, מובחן, נפרד" },
  { "en": "to distort", "he": "לעוות" },
  { "en": "to drag", "he": "לגרור, לסחוב, למשוך" },
  { "en": "to dread", "he": "לפחוד, להתיירא" },
  { "en": "to drift", "he": "להיסחף, לנדוד" },
  { "en": "drought", "he": "בצורת" },
  { "en": "to duplicate", "he": "לשכפל" },
  { "en": "eager", "he": "נלהב, להוט" },
  { "en": "emission", "he": "פליטה" },
  { "en": "to emit", "he": "לפלוט" },
  { "en": "to emphasize", "he": "להדגיש" },
  { "en": "enclosure", "he": "מכלאה, גידור" },
  { "en": "endeavor", "he": "מאמץ, ניסיון" },
  { "en": "era", "he": "עידן, תקופה" },
  { "en": "to erupt", "he": "להתפרץ (הר געש)" },
  { "en": "excessive", "he": "מוגזם, מופרז, עודף" },
  { "en": "to exert", "he": "להפעיל (השפעה או כוח), להתאמץ" },
  { "en": "to exhale", "he": "לנשוף" },
  { "en": "exile", "he": "גלות" },
  { "en": "to expand", "he": "להרחיב, להתפשט" },
  { "en": "to expire", "he": "לפוג" },
  { "en": "explicit", "he": "מפורש, ברור" },
  { "en": "to exploit", "he": "לנצל" },
  { "en": "to extend", "he": "להאריך, להתרחב, להשתרע, להושיט, להימשך, להתמתח, להתפרש" },
  { "en": "extension", "he": "שלוחה" },
  { "en": "to extinguish", "he": "לכבות" },
  { "en": "to fast", "he": "לצום" },
  { "en": "fatal", "he": "גורלי, קטלני" },
  { "en": "fin", "he": "סנפיר" },
  { "en": "to flee", "he": "להימלט" },
  { "en": "to flourish", "he": "לשגשג, ללבלב" },
  { "en": "fortnight", "he": "שבועיים" },
  { "en": "fraction", "he": "שבר פשוט (מתמטי), חלקיק" },
  { "en": "fracture", "he": "שבר (למשל שבר בעצם)" },
  { "en": "fragrance", "he": "ניחוח, ריח" },
  { "en": "fragrant", "he": "ריחני" },
  { "en": "fund", "he": "קרן, הון" },
  { "en": "to fund", "he": "לממן" },
  { "en": "fundamental", "he": "בסיסי, יסודי" },
  { "en": "to gather", "he": "לאסוף, להתאסף" },
  { "en": "to gaze", "he": "לבהות, להביט" },
  { "en": "genuine", "he": "אמיתי, מקורי, אותנטי" },
  { "en": "gills", "he": "זימים" },
  { "en": "greed", "he": "תאוות בצע, חמדנות" },
  { "en": "to greet", "he": "לברך לשלום" },
  { "en": "habitat", "he": "בית גידול, סביבת מחיה" },
  { "en": "hail", "he": "ברד" },
  { "en": "handicap", "he": "מגבלה, נכות" },
  { "en": "harbor", "he": "נמל" },
  { "en": "hazard", "he": "סכנה, סיכון" },
  { "en": "heir", "he": "יורש" },
  { "en": "herd", "he": "עדר" },
  { "en": "hereditary", "he": "תורשתי" },
  { "en": "to hijack", "he": "לחטוף (מטוס או כלי שיט)" },
  { "en": "hind", "he": "אחורי" },
  { "en": "hint", "he": "רמז" },
  { "en": "humidity", "he": "לחות" },
  { "en": "humility", "he": "ענווה, שפלות רוח" },
  { "en": "hump", "he": "דבשת" },
  { "en": "immense", "he": "עצום" },
  { "en": "impact", "he": "השפעה, רושם, התנגשות, פגיעה" },
  { "en": "to impair", "he": "לפגום, להחליש" },
  { "en": "implicit", "he": "מרומז, משתמע, עקיף" },
  { "en": "to imply", "he": "לרמז" },
  { "en": "to impose", "he": "(לכפות, לאכוף, להטיל) סנקציות" },
  { "en": "indignant", "he": "ממורמר, זועם" },
  { "en": "inevitable", "he": "בלתי נמנע" },
  { "en": "to inhale", "he": "לשאוף" },
  { "en": "to initiate", "he": "להתחיל, ליזום" },
  { "en": "initiative", "he": "יוזמה" },
  { "en": "innate", "he": "מולד" },
  { "en": "insect", "he": "חרק" },
  { "en": "insight", "he": "תובנה" },
  { "en": "intact", "he": "שלם" },
  { "en": "irrigation", "he": "השקיה" },
  { "en": "knot", "he": "קשר" },
  { "en": "litter", "he": "לכלוך, פסולת, אשפה, שגר (כל הגורים שנולדו באותה המלטה)" },
  { "en": "to loathe", "he": "לתעב" },
  { "en": "lyrics", "he": "מילים של שיר" },
  { "en": "malignant", "he": "ממאיר, זדוני, מרושע" },
  { "en": "mammal", "he": "יונק" },
  { "en": "manuscript", "he": "כתב יד (יצירה ספרותית)" },
  { "en": "marble", "he": "שיש, גולה" },
  { "en": "margin", "he": "שוליים" },
  { "en": "marginal", "he": "שולי" },
  { "en": "marsupial", "he": "חיית כיס" },
  { "en": "to merge", "he": "למזג, להתמזג" },
  { "en": "migration", "he": "נדידה, הגירה" },
  { "en": "mist", "he": "ערפל" },
  { "en": "to mock", "he": "לחקות, ללעוג, ללגלג" },
  { "en": "to modify", "he": "לשנות, להתאים" },
  { "en": "moist", "he": "לח" },
  { "en": "moisture", "he": "לחות" },
  { "en": "narrow", "he": "צר" },
  { "en": "nocturnal", "he": "לילי" },
  { "en": "notion", "he": "רעיון, מושג" },
  { "en": "nurse", "he": "אחות (מקצוע)" },
  { "en": "occasion", "he": "הזדמנות, אירוע, מקרה" },
  { "en": "occasionally", "he": "מדי פעם" },
  { "en": "to occupy", "he": "להעסיק, לשכון/להתגורר, להחזיק בשטח כבוש" },
  { "en": "to occur", "he": "לקרות" },
  { "en": "odor", "he": "ריח" },
  { "en": "to oppress", "he": "לדכא, לייסר" },
  { "en": "peak", "he": "פסגה, שיא" },
  { "en": "persecution", "he": "רדיפה, הצקה" },
  { "en": "to perspire", "he": "להזיע" },
  { "en": "to persist", "he": "להתעקש, להתמיד" },
  { "en": "petal", "he": "עלה כותרת" },
  { "en": "phenomenon", "he": "תופעה" },
  { "en": "plausible", "he": "סביר, מתקבל על הדעת" },
  { "en": "playwright", "he": "מחזאי" },
  { "en": "plot", "he": "עלילה, מזימה" },
  { "en": "predator", "he": "טורף" },
  { "en": "prescription", "he": "מרשם" },
  { "en": "prestige", "he": "יוקרה" },
  { "en": "to presume", "he": "להניח" },
  { "en": "prevalent", "he": "שכיח, נפוץ" },
  { "en": "prey", "he": "טרף" },
  { "en": "to prohibit", "he": "לאסור" },
  { "en": "prominent", "he": "בולט, חשוב" },
  { "en": "proverb", "he": "פתגם" },
  { "en": "punctual", "he": "דייקן" },
  { "en": "punctuation", "he": "פיסוק, ניקוד" },
  { "en": "quite", "he": "די, למדי" },
  { "en": "rapid", "he": "מהיר" },
  { "en": "rectangle", "he": "מלבן" },
  { "en": "to recur", "he": "לחזור על עצמו, לקרות שוב, להתרחש שנית" },
  { "en": "to regard", "he": "להתייחס, לייחס חשיבות" },
  { "en": "regardless (of)", "he": "בלי קשר ל" },
  { "en": "to rehabilitate", "he": "לשקם" },
  { "en": "to reinforce", "he": "לחזק, לתגבר" },
  { "en": "relic", "he": "שריד" },
  { "en": "remedy", "he": "תרופה" },
  { "en": "to repress", "he": "להדחיק" },
  { "en": "reptile", "he": "זוחל" },
  { "en": "to resume", "he": "לחדש, להתחיל מחדש, להמשיך" },
  { "en": "retaliation", "he": "נקמה, גמול" },
  { "en": "respiration", "he": "נשימה" },
  { "en": "to restore", "he": "לשקם, לשחזר" },
  { "en": "to restrain", "he": "לרסן" },
  { "en": "to restrict", "he": "להגביל" },
  { "en": "revenue", "he": "הכנסה, רווח, תשואה" },
  { "en": "to revise", "he": "לתקן, לשפר" },
  { "en": "rhyme", "he": "חרוז" },
  { "en": "rigid", "he": "נוקשה, קשיח" },
  { "en": "ritual", "he": "טקס" },
  { "en": "rodent", "he": "מכרסם" },
  { "en": "role", "he": "תפקיד" },
  { "en": "to roll", "he": "לגלגל, להתגלגל" },
  { "en": "to ruin", "he": "להרוס, להחריב" },
  { "en": "ruins", "he": "הריסות, חורבות" },
  { "en": "sacred", "he": "קדוש" },
  { "en": "scarce", "he": "נדיר, יקר המציאות" },
  { "en": "scenery", "he": "נוף" },
  { "en": "scholarship", "he": "מלגה" },
  { "en": "scribe", "he": "לבלר, פקיד, רשם, סופר" },
  { "en": "scripture", "he": "כתבים, כתבי הקודש" },
  { "en": "script", "he": "תסריט, כתב יד, עותק מקורי של יצירה" },
  { "en": "sculpture", "he": "פסל" },
  { "en": "secular", "he": "חילוני" },
  { "en": "to shrink", "he": "להתכווץ, לכווץ" },
  { "en": "sibling", "he": "אח/ות" },
  { "en": "skyscraper", "he": "גורד שחקים" },
  { "en": "slope", "he": "מדרון, שיפוע" },
  { "en": "to sort", "he": "למיין, לסווג" },
  { "en": "stagnant", "he": "קופא על השמרים" },
  { "en": "stale", "he": "מעופש, עבש" },
  { "en": "stem", "he": "גבעול, גזע" },
  { "en": "strict", "he": "קפדן, מחמיר, קשוח" },
  { "en": "to stem from", "he": "לנבוע מ" },
  { "en": "to strike", "he": "להכות, לשבות" },
  { "en": "stroke", "he": "שבץ" },
  { "en": "substance", "he": "חומר, תוכן" },
  { "en": "subtle", "he": "מעודן, עדין" },
  { "en": "suburb", "he": "פרבר" },
  { "en": "sufficient", "he": "מספיק, מספק" },
  { "en": "to surpass", "he": "להתעלות על" },
  { "en": "to surrender", "he": "להיכנע" },
  { "en": "syllable", "he": "הברה" },
  { "en": "tangible", "he": "מוחשי" },
  { "en": "tendency", "he": "נטייה" },
  { "en": "to tend", "he": "לנטות" },
  { "en": "term", "he": "מונח, מושג, תקופת כהונה, סמסטר, תנאי" },
  { "en": "to tend to", "he": "לטפל ב" },
  { "en": "terminal", "he": "מסוף, סופני, חשוך מרפא" },
  { "en": "to terminate", "he": "לסיים, לגמור, להסתיים" },
  { "en": "timber", "he": "עץ" },
  { "en": "thorough", "he": "יסודי" },
  { "en": "to thrive", "he": "לשגשג" },
  { "en": "toad", "he": "קרפד" },
  { "en": "to torment", "he": "לענות" },
  { "en": "transparent", "he": "שקוף" },
  { "en": "to undermine", "he": "לערער, לחתור תחת" },
  { "en": "upbringing", "he": "חינוך, גידול, טיפוח" },
  { "en": "urge", "he": "דחף" },
  { "en": "urgent", "he": "דחוף" },
  { "en": "vaccine", "he": "חיסון" },
  { "en": "vast", "he": "עצום" },
  { "en": "vicious", "he": "מרושע" },
  { "en": "to violate", "he": "להפר, לחלל, לטמא" },
  { "en": "vulture", "he": "עוף דורס" },
  { "en": "to worship", "he": "להעריץ, לסגוד" },
  { "en": "wound", "he": "פצע" },
  { "en": "yawn", "he": "פיהוק" }
]